{"bookId": "69f9cc23681eab6d6021a4d1", "moduleId": "69fd8840f7bd9ffc2364b2aa", "subjectId": "69fd8840f7bd9ffc2364b2ad", "chapterId": "69fd8840f7bd9ffc2364b7fa", "subject": "Physics", "chapter": "Circular Motion", "count": 2, "questions": [{"id": 303212, "subject": "Physics", "chapter": "Circular Motion", "exam": "Engineering", "examName": "Concepts Of Physics MCQ Edition [Volume 1]", "q": "A scooter, which together with its rider weighs $150 \\text{ kg}$, is travelling at $36 \\text{ km/hr}$. Determine the horizontal force on the scooter needed to successfully navigate a turn of radius $30 \\text{ m}$.", "options": ["$500 \\text{ N}$", "$50 \\text{ N}$", "$6480 \\text{ N}$", "$180 \\text{ N}$"], "answer": 0, "solution": "Mass of the scooter and rider, $m = 150 \\text{ kg}$<br><br>Velocity of the scooter, $v = 36 \\text{ km/hr} = 36 \\times \\dfrac{5}{18} \\text{ m/s} = 10 \\text{ m/s}$<br><br>Radius of the turn, $r = 30 \\text{ m}$<br><br>The horizontal force required to navigate the turn is the centripetal force, which is given by:<br><br>$F = \\dfrac{mv^2}{r}$<br><br>Substituting the given values:<br><br>$F = \\dfrac{150 \\times (10)^2}{30}$<br><br>$F = \\dfrac{150 \\times 100}{30} = 500 \\text{ N}$", "difficulty": "Medium", "source": "Concepts Of Physics MCQ Edition [Volume 1]", "_book": "69f9cc23681eab6d6021a4d1", "_chapterKey": "69f9cc23681eab6d6021a4d1__69fd8840f7bd9ffc2364b2aa__69fd8840f7bd9ffc2364b2ad__69fd8840f7bd9ffc2364b7fa"}, {"id": 303213, "subject": "Physics", "chapter": "Circular Motion", "exam": "Engineering", "examName": "Concepts Of Physics MCQ Edition [Volume 1]", "q": "A park has a radius of $10 \\text{ m}$. Determine the proper angle of banking if a vehicle travels around it at an average speed of $18 \\text{ km/hr}$.", "options": ["$\\tan^{-1}\\left(4\\right)$", "$\\tan^{-1}\\left(\\dfrac{1}{2}\\right)$", "$\\tan^{-1}\\left(\\dfrac{1}{4}\\right)$", "$\\tan^{-1}\\left(\\dfrac{1}{8}\\right)$"], "answer": 2, "solution": "Given radius of the park, $r = 10 \\text{ m}$<br><br>Speed of the vehicle, $v = 18 \\text{ km/hr} = 18 \\times \\dfrac{5}{18} \\text{ m/s} = 5 \\text{ m/s}$<br><br>The proper angle of banking $\\theta$ is given by the formula:<br><br>$\\tan \\theta = \\dfrac{v^2}{rg}$<br><br>Taking $g = 10 \\text{ m/s}^2$ and substituting the values:<br><br>$\\tan \\theta = \\dfrac{5^2}{10 \\times 10}$<br><br>$\\tan \\theta = \\dfrac{25}{100} = \\dfrac{1}{4}$<br><br>$\\theta = \\tan^{-1}\\left(\\dfrac{1}{4}\\right)$", "difficulty": "Medium", "source": "Concepts Of Physics MCQ Edition [Volume 1]", "_book": "69f9cc23681eab6d6021a4d1", "_chapterKey": "69f9cc23681eab6d6021a4d1__69fd8840f7bd9ffc2364b2aa__69fd8840f7bd9ffc2364b2ad__69fd8840f7bd9ffc2364b7fa"}]}