{"bookId": "68f1ce4cc729e5251bd00430", "moduleId": "68f8d4375694d9c689598ed9", "subjectId": "68f8d45d5694d9c689598efa", "chapterId": "68f8d4795694d9c689598f03", "subject": "Mathematics", "chapter": "Determinants", "count": 8, "questions": [{"id": 310822, "subject": "Mathematics", "chapter": "Determinants", "exam": "Engineering", "examName": "Most Important Selected Qs for JEE Advanced", "q": "Let $A, B, C$ be $\\mathrm{n} \\times \\mathrm{n}$ real matrices and are pairwise commutative and $\\mathrm{ABC}=\\mathrm{O}_{\\mathrm{n}}$ and if $\\lambda=\\operatorname{det}\\left(A^3+B^3+C^3\\right) \\cdot \\operatorname{det}(A+B+C)$ then", "options": ["$\\lambda\\gt0$", "$\\lambda \\lt 0$", "$\\lambda=0$", "$\\lambda \\in(-\\infty, \\infty)-\\{0\\}$"], "answer": 2, "solution": "$\\begin{aligned} & A^3+B^3+C^3=A^3+B^3+C^3-3 A B C=(A+B+C)\\left(A^2+B^2+C^2-A B-B C-C A\\right) \\\\ & =(A+B+C)\\left(A+\\omega B+\\omega^2 C\\right)\\left(A+\\omega^2 B+\\omega C\\right) \\quad\\{\\omega=\\text { cube root of unity }\\}\\end{aligned}$\n$=(A+B+C)\\left(A+\\omega B+\\omega^2 C\\right)\\left(\\overline{A+\\omega B+\\omega^2 C}\\right)$\n$\\begin{aligned} & =(A+B+C)\\left(A+\\omega B+\\omega^2 C\\right)\\left(A+\\omega B+\\omega^2 C\\right) \\\\ & \\text { then } \\operatorname{det}\\left(A^3+B^3+C^3\\right) \\cdot \\operatorname{det}(A+B+C)=\\operatorname{det}(A+B+C)^2 \\cdot \\operatorname{det}\\left(A+\\omega B+\\omega^2 C\\right) \\overline{\\operatorname{det}\\left(A+\\omega B+\\omega^2 C\\right)} \\\\ & =(\\operatorname{det}(A+B+C))^2 \\cdot\\left|\\operatorname{det}\\left(A+\\omega B+\\omega^2 C\\right)\\right|^2 \\geq 0\\end{aligned}$", "difficulty": "Medium", "source": "Most Important Selected Qs for JEE Advanced", "_book": "68f1ce4cc729e5251bd00430", "_chapterKey": "68f1ce4cc729e5251bd00430__68f8d4375694d9c689598ed9__68f8d45d5694d9c689598efa__68f8d4795694d9c689598f03"}, {"id": 310823, "subject": "Mathematics", "chapter": "Determinants", "exam": "Engineering", "examName": "Most Important Selected Qs for JEE Advanced", "q": "If the system of equation $2 x-y+z=0, x-2 y+z=0$ and $a x-y+2 z=0$ has infinitely many solutions and $f(x)$ be a continuous function such that $f(5+x)+f(x)=2 \\forall x \\in R$, then $\\int_0^{-2 a} f(x) d x$ is equal to:", "options": ["-10", "$-2 a$", "$\\int_0^a[x] d x$", "$2 a$\n[Note: $[k]$ denotes greatest integer less than or equal to $k$.]"], "answer": 1, "solution": "$\\begin{aligned} & \\Delta=0, \\quad a=5 \\\\ & \\int_0^{-10} f(x) d x=\\int_0^{-5} f(x) d x+\\int_{-5}^{-10} f(x) d x=\\int_{-5}^{-10} f(x+5) d x+\\int_{-5}^{-10} f(x) d x=2 \\int_{-5}^{-10} d x=-10\\end{aligned}$", "difficulty": "Medium", "source": "Most Important Selected Qs for JEE Advanced", "_book": "68f1ce4cc729e5251bd00430", "_chapterKey": "68f1ce4cc729e5251bd00430__68f8d4375694d9c689598ed9__68f8d45d5694d9c689598efa__68f8d4795694d9c689598f03"}, {"id": 310824, "subject": "Mathematics", "chapter": "Determinants", "exam": "Engineering", "examName": "Most Important Selected Qs for JEE Advanced", "q": "If the system of equations, $a^2 x-b y=a^2-b \\& b x-b^2 y=2+4 b$ possess an infinite number of solutions then the possible values of 'a' and 'b' are", "options": ["$\\mathrm{a}=1, \\mathrm{~b}=-1$", "$a=1, b=-2$", "$a=-1, b=-1$", "$a=-1, b=-2$"], "answer": 3, "solution": "$\\frac{a^2}{b}=\\frac{b}{b^2}=\\frac{a^2-b}{2+4 b} \\Rightarrow a^2 b^2=b^2 \\Rightarrow b^2\\left(a^2-1\\right) \\Rightarrow a=1$ or $-1 \\& b=0$,\nif $\\mathrm{a}=1$ then $2+4 \\mathrm{~b}=\\mathrm{b}-\\mathrm{b}^2 \\Rightarrow \\mathrm{~b}^2+3 \\mathrm{~b}+2=0 \\Rightarrow \\mathrm{~b}=-2$ or -1 ;\nif $a=-1$ then $b=-2$ or -1", "difficulty": "Easy", "source": "Most Important Selected Qs for JEE Advanced", "_book": "68f1ce4cc729e5251bd00430", "_chapterKey": "68f1ce4cc729e5251bd00430__68f8d4375694d9c689598ed9__68f8d45d5694d9c689598efa__68f8d4795694d9c689598f03"}, {"id": 310825, "subject": "Mathematics", "chapter": "Determinants", "exam": "Engineering", "examName": "Most Important Selected Qs for JEE Advanced", "q": "$\\left|\\begin{array}{ccc}2 a & 2 b & b-c \\\\ 2 b & 2 a & a+c \\\\ a+b & a+b & b\\end{array}\\right|$ is divisible by -", "options": ["(a-b)", "$(a-b)^2$", "$a+b$", "$(a+b+c)$"], "answer": 2, "solution": "$\\Delta=\\left|\\begin{array}{ccc}2 \\mathrm{a} & 2 \\mathrm{~b} & \\mathrm{~b}-\\mathrm{c} \\\\ 2 \\mathrm{~b} & 2 \\mathrm{a} & \\mathrm{a}+\\mathrm{c} \\\\ \\mathrm{a}+\\mathrm{b} & \\mathrm{a}+\\mathrm{b} & \\mathrm{b}\\end{array}\\right|$\n$\\begin{aligned} & R_2 \\rightarrow R_2+R_1 \\\\ & \\Delta=\\left|\\begin{array}{ccc}2 a & 2 b & b-c \\\\ 2(a+b) & 2(a+b) & a+b \\\\ a+b & a+b & b\\end{array}\\right| \\\\ & \\Delta=(a+b)\\left|\\begin{array}{ccc}2 a & 2 b & b-c \\\\ 2 & 2 & 1 \\\\ a+b & a+b & b\\end{array}\\right| \\\\ & C_1 \\rightarrow C_1-C_2 \\\\ & =(a+b)\\left|\\begin{array}{ccc}2(a-b) & 2 b & b-c \\\\ 0 & 2 & 1 \\\\ 0 & a+b & b\\end{array}\\right| \\\\ & =(a+b) \\cdot 2(a-b)(2 b-a-b) \\\\ & = \\\\ & =2(a+b)(a-b)(b-a)=-2(a+b)(a-b)^2 .\\end{aligned}$", "difficulty": "Medium", "source": "Most Important Selected Qs for JEE Advanced", "_book": "68f1ce4cc729e5251bd00430", "_chapterKey": "68f1ce4cc729e5251bd00430__68f8d4375694d9c689598ed9__68f8d45d5694d9c689598efa__68f8d4795694d9c689598f03"}, {"id": 310826, "subject": "Mathematics", "chapter": "Determinants", "exam": "Engineering", "examName": "Most Important Selected Qs for JEE Advanced", "q": "If $\\left|\\begin{array}{ccc}x^2-5 x+3 & 2 x-5 & 3 \\\\ 3 x^2+x+4 & 6 x+1 & 9 \\\\ 7 x^2-6 x+9 & 14 x-6 & 21\\end{array}\\right|=a x^3+b x^2+c x+d$ then which of the following are correct?", "options": ["$a=0$", "$b=0$", "$c=0$", "$d=0$"], "answer": 2, "solution": "$f(x)=\\left|\\begin{array}{ccc}x^2-5 x+3 & 2 x-5 & 3 \\\\ 3 x^2+x+4 & 6 x+1 & 9 \\\\ 7 x^2-6 x+9 & 14 x-6 & 21\\end{array}\\right|$\n$f^{\\prime}(x)=0$\n$\\Rightarrow f(x)$ is a constant polynomial and $f(0) \\neq 0$\n$\\Rightarrow d \\neq 0$", "difficulty": "Medium", "source": "Most Important Selected Qs for JEE Advanced", "_book": "68f1ce4cc729e5251bd00430", "_chapterKey": "68f1ce4cc729e5251bd00430__68f8d4375694d9c689598ed9__68f8d45d5694d9c689598efa__68f8d4795694d9c689598f03"}, {"id": 310827, "subject": "Mathematics", "chapter": "Determinants", "exam": "Engineering", "examName": "Most Important Selected Qs for JEE Advanced", "q": "Let $f(x)=\\left|\\begin{array}{ccc}2 \\sin x & \\sin ^2 x & 0 \\\\ 1 & 2 \\sin x & \\sin ^2 x \\\\ 0 & 1 & 2 \\sin x\\end{array}\\right|$, then", "options": ["$f(x)$ is independent of $x$", "$f^{\\prime}(\\pi / 2)=0$", "$\\int_{-\\pi / 2}^{\\pi / 2} f(x) d x=0$", "Tangent to the curve $y=f(x)$ at $x=0$ is $y=0$"], "answer": 3, "solution": "$f(x)=\\left|\\begin{array}{ccc}2 \\sin x & \\sin ^2 x & 0 \\\\ 1 & 2 \\sin x & \\sin ^2 x \\\\ 0 & 1 & 2 \\sin x\\end{array}\\right|=2 \\sin x\\left(4 \\sin ^2 x-\\sin ^2 x\\right)-\\sin ^2 x(2 \\sin x)=6 \\sin ^3 x-2 \\sin ^3 x$\n$\\begin{aligned} & f(x)=4 \\sin ^3 x \\\\ & \\Rightarrow f^{\\prime}(x)=12 \\sin ^2 x \\cos x\\end{aligned}$\n(B) $f^{\\prime}(\\pi / 2)=12 \\sin ^2(\\pi / 2) \\cos (\\pi / 2)=0$\n(C) $f(-x)=-f(x)$ odd function\n$\\therefore \\quad \\int_{\\frac{-\\pi}{2}}^{\\frac{\\pi}{2}} f(x) d x=0$\n(D) at $x=0, y=0$\n$\\Rightarrow\\left(\\frac{d y}{d x}\\right)_{(0,0)}=0$ tangent at $(0,0)$\n$\\begin{aligned} & y-0=\\left(\\frac{d y}{d x}\\right)_{(0,0)}(x-0) \\\\ & \\Rightarrow y=0\\end{aligned}$", "difficulty": "Medium", "source": "Most Important Selected Qs for JEE Advanced", "_book": "68f1ce4cc729e5251bd00430", "_chapterKey": "68f1ce4cc729e5251bd00430__68f8d4375694d9c689598ed9__68f8d45d5694d9c689598efa__68f8d4795694d9c689598f03"}, {"id": 310828, "subject": "Mathematics", "chapter": "Determinants", "exam": "Engineering", "examName": "Most Important Selected Qs for JEE Advanced", "q": "System of equation\n$\\begin{aligned} & x+3 y+2 z=6 \\\\ & x+\\lambda y+2 z=7 \\\\ & x+3 y+2 z=\\mu \\text { has }\\end{aligned}$", "options": ["Unique solution if $\\lambda=2, \\mu \\neq 6$", "Infinitely many solution if $\\lambda=4, \\mu=6$", "No solution if $\\lambda=5, \\mu=7$", "No solution if $\\lambda=3, \\mu=5$"], "answer": 3, "solution": "$x+3 y+2 z=6$....(i)\n$x+\\lambda y+2 z=7$....(ii)\n$x+3 y+2 z=\\mu$....(iii)\n(A) If $\\lambda=2$, then $D=0$, therefore unique solution is not possible\n(B) If $\\lambda=4, \\mu=6$\n$\\begin{aligned} & x+3 y=6-2 z \\\\ & x+4 y=7-2 z\\end{aligned}$\n$\\therefore \\quad y=1$ and $x=3-2 z$\nSubstituting in equation (iii)\n$3-2 z+3+2 z=6$ is satisfied\n$\\therefore \\quad$ infinite solutions\n(C) $\\lambda=5, \\mu=7$\nconsider equation (ii) and (iii)\n$\\begin{aligned} & x+5 y=7-2 z \\\\ & x+3 y=7-2 z\\end{aligned}$\n$\\therefore \\quad y=0, x=7-2 z$ are solution\nsub. in (i)\n$7-2 z+2 z=6$ does not satisfy\n$\\therefore \\quad$ no solution\n(D) if $\\lambda=3, \\mu=5$\nthen equation (i) and (ii) have no solution\n$\\therefore \\quad$ no solution", "difficulty": "Medium", "source": "Most Important Selected Qs for JEE Advanced", "_book": "68f1ce4cc729e5251bd00430", "_chapterKey": "68f1ce4cc729e5251bd00430__68f8d4375694d9c689598ed9__68f8d45d5694d9c689598efa__68f8d4795694d9c689598f03"}, {"id": 310829, "subject": "Mathematics", "chapter": "Determinants", "exam": "Engineering", "examName": "Most Important Selected Qs for JEE Advanced", "q": "If $x$ is real and $\\Delta(x)=\\left|\\begin{array}{ccc}x^2+x & 2 x-1 & x+3 \\\\ 3 x+1 & x^2+2 & x^3-3 \\\\ x-3 & x^2+4 & 2 x\\end{array}\\right|=a_0 x^7+a_1 x^6+a_2 x^5+\\ldots \\ldots+a_6 x+a_7$, then:", "options": ["$a_7=21$", "$\\sum_{k=0}^6 a_k=111$", "$\\Delta(-1)=32$", "$\\Delta(1)=121$"], "answer": 1, "solution": "(1)\n$$\na_7=\\Delta(0)=\\left|\\begin{array}{ccc}\n0 & -1 & 3 \\\\\n1 & 2 & -3 \\\\\n-3 & 4 & 0\n\\end{array}\\right|=21\n$$\n(2) and (4) $\\Delta(1)=\\left|\\begin{array}{ccc}2 & 1 & 4 \\\\ 4 & 3 & -2 \\\\ -2 & 5 & 2\\end{array}\\right|=132=\\sum_{k=0}^7 a_k$\nNow, $\\quad \\sum_{k=0}^6 a_k=\\sum_{k=0}^7 a_k-a_7=132-21=111$\n(3) $\\Delta(-1)=\\left|\\begin{array}{ccc}0 & -3 & 2 \\\\ -2 & 3 & -4 \\\\ -4 & 5 & -2\\end{array}\\right|=-32$", "difficulty": "Medium", "source": "Most Important Selected Qs for JEE Advanced", "_book": "68f1ce4cc729e5251bd00430", "_chapterKey": "68f1ce4cc729e5251bd00430__68f8d4375694d9c689598ed9__68f8d45d5694d9c689598efa__68f8d4795694d9c689598f03"}]}