{"bookId": "68f1ce4cc729e5251bd00430", "moduleId": "68f8d633530ed81e1968d783", "subjectId": "68f8d64a530ed81e1968d79c", "chapterId": "68f8d663530ed81e1968d7a6", "subject": "Mathematics", "chapter": "Ellipse", "count": 9, "questions": [{"id": 312429, "subject": "Mathematics", "chapter": "Ellipse", "exam": "Engineering", "examName": "Most Important Selected Qs for JEE Advanced", "q": "<strong>Paragraph:</strong>An ellipse whose major axis is parallel to $x$-axis such that segment of a focal chord are 1 and 2 units. The line $\\frac{x}{a}+\\frac{y}{b}+\\frac{1}{c}=0$ are the chords of the ellipse such that a, c, b are in H.P. and are bisected by the point at which they are concurrent, the equation of auxiliary circle is $2 x^2+2 y^2+4 p x+4 q y-16 p+1=0$ then<strong>Question:</strong>The centre of ellipse is", "options": ["$(1,-1)$", "$(1,1)$", "$\\left(\\frac{1}{2}, \\frac{1}{2}\\right)$", "$\\left(-\\frac{1}{2},-\\frac{1}{2}\\right)$"], "answer": 3, "solution": "$\\mathrm{a}, \\mathrm{c}, \\mathrm{b}$ are in H.P.\n$\\Rightarrow \\frac{2}{c}=\\frac{1}{a}+\\frac{1}{b}$\nLine $\\frac{x}{a}+\\frac{y}{b}+\\frac{1}{c}=0$ passes through a fixed point $\\left(-\\frac{1}{2},-\\frac{1}{2}\\right)$\nSo centre of ellipse is $\\left(-\\frac{1}{2},-\\frac{1}{2}\\right)$\nWhich is also centre of auxiliary circle\n$\\Rightarrow \\mathrm{p}=\\frac{1}{2}, \\mathrm{q}=\\frac{1}{2}$ radius of auxiliary circle $=2$\n$\\therefore$ Length of major axis $=4$ also it segment of focal chord are 1,2\n$\\Rightarrow \\frac{1}{1}+\\frac{1}{2}=\\frac{4}{b^2} \\Rightarrow b^2=\\frac{8}{3}$\nDirector circle $\\left(x+\\frac{1}{2}\\right)^2+\\left(y+\\frac{1}{2}\\right)^2=\\frac{8}{3}+4$", "difficulty": "Hard", "source": "Most Important Selected Qs for JEE Advanced", "_book": "68f1ce4cc729e5251bd00430", "_chapterKey": "68f1ce4cc729e5251bd00430__68f8d633530ed81e1968d783__68f8d64a530ed81e1968d79c__68f8d663530ed81e1968d7a6"}, {"id": 312430, "subject": "Mathematics", "chapter": "Ellipse", "exam": "Engineering", "examName": "Most Important Selected Qs for JEE Advanced", "q": "<strong>Paragraph:</strong>\nRead the following write up carefully and answer the following questions: If $a^2+\\mathrm{by}^2+2 \\mathrm{hxy}+2 \\mathrm{gx}+2 \\mathrm{fy}+\\mathrm{c}=0$ represents an ellipse, then $\\mathrm{h}^2 \\lt \\mathrm{ab}$ and $\\mathrm{abc}+2 \\mathrm{fgh}-\\mathrm{af}^2-\\mathrm{bg}^2-\\mathrm{ch}^2 \\neq 0$. If for every point ( $\\mathrm{x}_1, \\mathrm{y}_1$ ) satisfying above equation $\\left(2 h-x_1, 2 k-y_1\\right)$ also satisfy it, then $(h, k)$ is centre of it. The length of semi major axis and minor axis is nothing but the maximum and minimum value of the distance of a point lying on the curve from its centre.<strong>Question:</strong>\nIf the given ellipse is rotated so that it has its major axis coincident with x-axis, then its equation becomes", "options": ["$3\\left(x^2+y^2-1\\right)=\\left(y^2-x^2+1\\right) \\sqrt{2}$", "$3\\left(x^2+y^2-1\\right)=\\left(y^2-x^2-1\\right) \\sqrt{2}$", "$3\\left(x^2+y^2-1\\right)=\\left(y^2-x^2-1\\right) \\sqrt{2}$", "$\\sqrt{2}\\left(x^2-y^2+1\\right)=3\\left(x^2+y^2-1\\right)$"], "answer": 3, "solution": "Required equation is $\\frac{x^2}{\\frac{3+\\sqrt{2}}{3-\\sqrt{2}}}+y^2=1$", "difficulty": "Medium", "source": "Most Important Selected Qs for JEE Advanced", "_book": "68f1ce4cc729e5251bd00430", "_chapterKey": "68f1ce4cc729e5251bd00430__68f8d633530ed81e1968d783__68f8d64a530ed81e1968d79c__68f8d663530ed81e1968d7a6"}, {"id": 312431, "subject": "Mathematics", "chapter": "Ellipse", "exam": "Engineering", "examName": "Most Important Selected Qs for JEE Advanced", "q": "<strong>Paragraph:</strong>\nRead the following write up carefully and answer the following questions: If $a^2+\\mathrm{by}^2+2 \\mathrm{hxy}+2 \\mathrm{gx}+2 \\mathrm{fy}+\\mathrm{c}=0$ represents an ellipse, then $\\mathrm{h}^2 \\lt \\mathrm{ab}$ and $\\mathrm{abc}+2 \\mathrm{fgh}-\\mathrm{af}^2-\\mathrm{bg}^2-\\mathrm{ch}^2 \\neq 0$. If for every point ( $\\mathrm{x}_1, \\mathrm{y}_1$ ) satisfying above equation $\\left(2 h-x_1, 2 k-y_1\\right)$ also satisfy it, then $(h, k)$ is centre of it. The length of semi major axis and minor axis is nothing but the maximum and minimum value of the distance of a point lying on the curve from its centre.<strong>Question:</strong>\nThe maximum area of the circle lying inside the given ellipse is", "options": ["$\\pi$", "$\\frac{\\pi}{2}$", "$\\pi\\left(\\frac{3+\\sqrt{2}}{3-\\sqrt{2}}\\right)$", "$\\pi\\left(\\frac{3-\\sqrt{2}}{3+\\sqrt{2}}\\right)$"], "answer": 0, "solution": "Centre of circle be origin and its radius is the length of semi minor axis Hence area $=\\pi$", "difficulty": "Medium", "source": "Most Important Selected Qs for JEE Advanced", "_book": "68f1ce4cc729e5251bd00430", "_chapterKey": "68f1ce4cc729e5251bd00430__68f8d633530ed81e1968d783__68f8d64a530ed81e1968d79c__68f8d663530ed81e1968d7a6"}, {"id": 312432, "subject": "Mathematics", "chapter": "Ellipse", "exam": "Engineering", "examName": "Most Important Selected Qs for JEE Advanced", "q": "<strong>Paragraph:</strong>An ellipse whose major axis is parallel to $x$-axis such that segment of a focal chord are 1 and 2 units. The line $\\frac{x}{a}+\\frac{y}{b}+\\frac{1}{c}=0$ are the chords of the ellipse such that a, c, b are in H.P. and are bisected by the point at which they are concurrent, the equation of auxiliary circle is $2 x^2+2 y^2+4 p x+4 q y-16 p+1=0$ then<strong>Question:</strong>Equation of director circle is", "options": ["$\\mathrm{x}^2+\\mathrm{y}^2-\\mathrm{x}-\\mathrm{y}-\\frac{37}{6}=0$", "$x^2+y^2+x+y+\\frac{37}{6}=0$", "$x^2+y^2+x+y-\\frac{37}{6}=0$", "$x^2+b^2-x-y+\\frac{37}{6}=0$"], "answer": 2, "solution": "$\\mathrm{a}, \\mathrm{c}, \\mathrm{b}$ are in H.P.\n$\\Rightarrow \\frac{2}{c}=\\frac{1}{a}+\\frac{1}{b}$\nLine $\\frac{x}{a}+\\frac{y}{b}+\\frac{1}{c}=0$ passes through a fixed point $\\left(-\\frac{1}{2},-\\frac{1}{2}\\right)$\nSo centre of ellipse is $\\left(-\\frac{1}{2},-\\frac{1}{2}\\right)$\nWhich is also centre of auxiliary circle\n$\\Rightarrow \\mathrm{p}=\\frac{1}{2}, \\mathrm{q}=\\frac{1}{2}$ radius of auxiliary circle $=2$\n$\\therefore$ Length of major axis $=4$ also it segment of focal chord are 1,2\n$\\Rightarrow \\frac{1}{1}+\\frac{1}{2}=\\frac{4}{b^2} \\Rightarrow b^2=\\frac{8}{3}$\nDirector circle $\\left(x+\\frac{1}{2}\\right)^2+\\left(y+\\frac{1}{2}\\right)^2=\\frac{8}{3}+4$", "difficulty": "Hard", "source": "Most Important Selected Qs for JEE Advanced", "_book": "68f1ce4cc729e5251bd00430", "_chapterKey": "68f1ce4cc729e5251bd00430__68f8d633530ed81e1968d783__68f8d64a530ed81e1968d79c__68f8d663530ed81e1968d7a6"}, {"id": 312433, "subject": "Mathematics", "chapter": "Ellipse", "exam": "Engineering", "examName": "Most Important Selected Qs for JEE Advanced", "q": "<strong>Paragraph:</strong>\nRead the following write up carefully and answer the following questions: If $a^2+\\mathrm{by}^2+2 \\mathrm{hxy}+2 \\mathrm{gx}+2 \\mathrm{fy}+\\mathrm{c}=0$ represents an ellipse, then $\\mathrm{h}^2 \\lt \\mathrm{ab}$ and $\\mathrm{abc}+2 \\mathrm{fgh}-\\mathrm{af}^2-\\mathrm{bg}^2-\\mathrm{ch}^2 \\neq 0$. If for every point ( $\\mathrm{x}_1, \\mathrm{y}_1$ ) satisfying above equation $\\left(2 h-x_1, 2 k-y_1\\right)$ also satisfy it, then $(h, k)$ is centre of it. The length of semi major axis and minor axis is nothing but the maximum and minimum value of the distance of a point lying on the curve from its centre.<strong>Question:</strong>\nFor the ellipse $2 x^2-2 x y+4 y^2-(3+\\sqrt{2})=0$, the inclination of major axis of it with $x$-axis is", "options": ["$\\frac{\\pi}{12}$", "$\\frac{\\pi}{8}$", "$\\frac{3 \\pi}{8}$", "$\\frac{5 \\pi}{8}$"], "answer": 1, "solution": "Taking point $(r \\cos \\theta, r \\sin \\theta)$, we get\n$$\n\\begin{aligned}\n& r^2=\\frac{3+\\sqrt{2}}{3-\\sqrt{2} \\sin \\left(2 \\theta+\\frac{\\pi}{4}\\right)} \\\\\n& r_{\\max }=\\sqrt{\\frac{3+\\sqrt{2}}{3-\\sqrt{2}}}, r_{\\min }=1\n\\end{aligned}\n$$\n\nMax exist when $2 \\theta+\\frac{\\pi}{4}=\\frac{\\pi}{2} \\Rightarrow \\theta=\\frac{\\pi}{8}$", "difficulty": "Medium", "source": "Most Important Selected Qs for JEE Advanced", "_book": "68f1ce4cc729e5251bd00430", "_chapterKey": "68f1ce4cc729e5251bd00430__68f8d633530ed81e1968d783__68f8d64a530ed81e1968d79c__68f8d663530ed81e1968d7a6"}, {"id": 312434, "subject": "Mathematics", "chapter": "Ellipse", "exam": "Engineering", "examName": "Most Important Selected Qs for JEE Advanced", "q": "<strong>Paragraph:</strong>\nOn the ellipse $E=\\frac{x^2}{64}+\\frac{y^2}{9}=1$, tangents drawn at the point $P_1, P_2, P_3, \\ldots \\ldots P_n$ on the ellipse intersecting the major axis at $T_1, T_2, T_3 \\ldots \\ldots, T_n$ respectively.<strong>Question:</strong>\nIf the value of $\\sum_{i=1}^n \\frac{\\operatorname{Area}\\left(\\Delta P_i T_i S\\right) \\cdot \\operatorname{Area}\\left(\\Delta P_i T_i S^{\\prime}\\right)}{\\left(P_i T_i\\right)^2}=18$. where $S$ and $S^{\\prime}$ represents the foci of the ellipse, then ' $n$ ' equal to:", "options": ["6", "8", "10", "12"], "answer": 1, "solution": "$\\begin{aligned} & \\text { (i) } \\quad S A \\perp P_i T_i \\\\ & S^{\\prime} B \\perp P_i T_i\\end{aligned}$\n<img src=\"https://cdn-question-pool.getmarks.app/modules/ms/ja/hc_VEc0fAFkmgL_gt4se-ZrxzH2KwHbHMwUKxP6CEJY.original.fullsize.png\"><br>\n$$\n\\begin{aligned}\n& A_1=\\operatorname{Area}\\left(\\Delta S P_i T_i\\right)=\\frac{1}{2} \\times S A \\times P_i T_i \\\\\n& A_2=\\operatorname{Area}\\left(\\Delta S^{\\prime} P_i T_i\\right)=\\frac{1}{2} \\times S^{\\prime} B \\times P_i T_i \\\\\n& \\frac{A_1 A_2}{\\left(P_i T_i\\right)^2}=\\frac{b^2}{4} \\quad\\left(S A \\times S^{\\prime} B=b^2\\right) \\\\\n& \\sum \\frac{A_1 A_2}{\\left(P_i T_i\\right)^2}=18 \\quad \\Rightarrow \\quad \\frac{n b^2}{4}=18 \\quad \\Rightarrow n=8\n\\end{aligned}\n$$\n(ii) Tangent at $\\left(a e, \\frac{b^2}{a}\\right)$\n$$\n\\frac{x \\cdot a e}{a^2}+\\frac{y \\cdot b^2}{a \\cdot b^2}=1\n$$<img src=\"https://cdn-question-pool.getmarks.app/modules/ms/ja/deU1P7652c0n7gYlI5Hcs2o-XG8dW3sZsWkBh1Euqvw.original.fullsize.png\"><br>\n$\\begin{aligned} & \\Rightarrow \\quad e x+y=a \\\\ & A=\\frac{2 a}{e} \\cdot \\frac{2 a}{2}=\\frac{2 a^2}{e}=2 \\times 64 \\times \\frac{8}{\\sqrt{55}} \\quad \\Rightarrow \\quad \\lambda=64 \\\\ & \\end{aligned}$", "difficulty": "Medium", "source": "Most Important Selected Qs for JEE Advanced", "_book": "68f1ce4cc729e5251bd00430", "_chapterKey": "68f1ce4cc729e5251bd00430__68f8d633530ed81e1968d783__68f8d64a530ed81e1968d79c__68f8d663530ed81e1968d7a6"}, {"id": 312435, "subject": "Mathematics", "chapter": "Ellipse", "exam": "Engineering", "examName": "Most Important Selected Qs for JEE Advanced", "q": "<strong>Paragraph:</strong>\nOn the ellipse $E=\\frac{x^2}{64}+\\frac{y^2}{9}=1$, tangents drawn at the point $P_1, P_2, P_3, \\ldots \\ldots P_n$ on the ellipse intersecting the major axis at $T_1, T_2, T_3 \\ldots \\ldots, T_n$ respectively.<strong>Question:</strong>\nIf the area of the quadrilateral formed by the tangents at the ends of the latus rectum of the ellipse $E$, is $\\frac{16 \\lambda}{\\sqrt{55}}$, then $\\lambda$ equals:", "options": ["8", "16", "32", "64"], "answer": 3, "solution": "$\\begin{aligned} & \\text { (i) } \\quad S A \\perp P_i T_i \\\\ & S^{\\prime} B \\perp P_i T_i\\end{aligned}$\n<img src=\"https://cdn-question-pool.getmarks.app/modules/ms/ja/hc_VEc0fAFkmgL_gt4se-ZrxzH2KwHbHMwUKxP6CEJY.original.fullsize.png\"><br>\n$$\n\\begin{aligned}\n& A_1=\\operatorname{Area}\\left(\\Delta S P_i T_i\\right)=\\frac{1}{2} \\times S A \\times P_i T_i \\\\\n& A_2=\\operatorname{Area}\\left(\\Delta S^{\\prime} P_i T_i\\right)=\\frac{1}{2} \\times S^{\\prime} B \\times P_i T_i \\\\\n& \\frac{A_1 A_2}{\\left(P_i T_i\\right)^2}=\\frac{b^2}{4} \\quad\\left(S A \\times S^{\\prime} B=b^2\\right) \\\\\n& \\sum \\frac{A_1 A_2}{\\left(P_i T_i\\right)^2}=18 \\quad \\Rightarrow \\quad \\frac{n b^2}{4}=18 \\quad \\Rightarrow n=8\n\\end{aligned}\n$$\n(ii) Tangent at $\\left(a e, \\frac{b^2}{a}\\right)$\n$$\n\\frac{x \\cdot a e}{a^2}+\\frac{y \\cdot b^2}{a \\cdot b^2}=1\n$$<img src=\"https://cdn-question-pool.getmarks.app/modules/ms/ja/deU1P7652c0n7gYlI5Hcs2o-XG8dW3sZsWkBh1Euqvw.original.fullsize.png\"><br>\n$\\begin{aligned} & \\Rightarrow \\quad e x+y=a \\\\ & A=\\frac{2 a}{e} \\cdot \\frac{2 a}{2}=\\frac{2 a^2}{e}=2 \\times 64 \\times \\frac{8}{\\sqrt{55}} \\quad \\Rightarrow \\quad \\lambda=64 \\\\ & \\end{aligned}$", "difficulty": "Medium", "source": "Most Important Selected Qs for JEE Advanced", "_book": "68f1ce4cc729e5251bd00430", "_chapterKey": "68f1ce4cc729e5251bd00430__68f8d633530ed81e1968d783__68f8d64a530ed81e1968d79c__68f8d663530ed81e1968d7a6"}, {"id": 312436, "subject": "Mathematics", "chapter": "Ellipse", "exam": "Engineering", "examName": "Most Important Selected Qs for JEE Advanced", "q": "<strong>Paragraph:</strong>\nTangents are drawn from a variable point $P$ to the ellipse $x^2+4 y^2=4$ meeting it at $Q \\& R$. So $Q R$ is chord of contact of pair of tangents drawn from P .\nOn the basis of above information answer the following :<strong>Question:</strong>\nIf the sum of inclination of PQ and PR is constant $\\left(\\neq 90^{\\circ}\\right)$, then the locus of P is a -", "options": ["hyperbola", "ellipse", "parabola", "circle"], "answer": 0, "solution": "Ellipse $\\frac{x^2}{4}+y^2=1$\nLet $\\mathrm{P}(\\mathrm{h}, \\mathrm{k})$ and equation of any tangent is\n$\\begin{aligned}\n& y=m x \\pm \\sqrt{4 m^2+1} \\Rightarrow(k-m h)^2=4 m^2+1 \\\\\n& \\Rightarrow \\mathrm{~m}^2\\left(\\mathrm{~h}^2-4\\right)-2 \\mathrm{mkh}+\\left(\\mathrm{k}^2-1\\right)=0 \\\\\n& \\theta_1+\\theta_2=\\alpha \\\\\n& \\tan \\left(\\theta_1+\\theta_2\\right)=\\tan \\alpha \\\\\n& \\Rightarrow \\frac{\\mathrm{m}_1+\\mathrm{m}_2}{1-\\mathrm{m}_1 \\mathrm{~m}_2}=\\tan \\alpha \\Rightarrow \\frac{\\frac{2 \\mathrm{hk}}{\\mathrm{~h}^2-4}}{1-\\frac{\\mathrm{k}^2-1}{\\mathrm{~h}^2-4}}=\\tan \\alpha\n\\end{aligned}$\n$\\begin{aligned}\n& \\Rightarrow \\quad 2 \\mathrm{xy}=\\tan \\alpha\\left(\\mathrm{x}^2-\\mathrm{y}^2-3\\right) \\\\\n& \\Rightarrow \\quad \\mathrm{x}^2-2 \\mathrm{xy} \\cot \\alpha-\\mathrm{y}^2=3 \\\\\n& \\Delta=3-0-0-0+3(\\cot \\alpha)^2 \\neq 0\n\\end{aligned}$\n$\\mathrm{H}^2\\gt\\mathrm{AB}$ so hyperbola", "difficulty": "Medium", "source": "Most Important Selected Qs for JEE Advanced", "_book": "68f1ce4cc729e5251bd00430", "_chapterKey": "68f1ce4cc729e5251bd00430__68f8d633530ed81e1968d783__68f8d64a530ed81e1968d79c__68f8d663530ed81e1968d7a6"}, {"id": 312437, "subject": "Mathematics", "chapter": "Ellipse", "exam": "Engineering", "examName": "Most Important Selected Qs for JEE Advanced", "q": "<strong>Paragraph:</strong>\nTangents are drawn from a variable point $P$ to the ellipse $x^2+4 y^2=4$ meeting it at $Q \\& R$. So $Q R$ is chord of contact of pair of tangents drawn from P .\nOn the basis of above information answer the following :<strong>Question:</strong>\nIf angle between $\\mathrm{PQ} \\& \\mathrm{PR}$ is $45^{\\circ}$, then locus of P is -", "options": ["$\\left(x^2+y^2-5\\right)=4\\left(x^2+4 y^2-4\\right)^2$", "$\\left(x^2+y^2-5\\right)^2=4\\left(x^2+4 y^2-4\\right)$", "$\\left(x^2+y^2-4\\right)=5\\left(x^2+4 y^2-4\\right)^2$", "$x^2+4 y^2=5$"], "answer": 1, "solution": "$\\begin{aligned} & \\tan 45^{\\circ}=\\left|\\frac{m_1-m_2}{1+m_1 m_2}\\right| \\\\ & \\left(1+\\mathrm{m}_1 \\mathrm{~m}_2\\right)^2=\\left(\\mathrm{m}_1+\\mathrm{m}_2\\right)^2-4 \\mathrm{~m}_1 \\mathrm{~m}_2 \\\\ & \\left(1+\\frac{\\mathrm{k}^2-1}{\\mathrm{~h}^2-4}\\right)^2=\\left(\\frac{2 \\mathrm{hk}}{\\mathrm{h}^2-4}\\right)^2-4 \\frac{\\mathrm{k}^2-1}{\\mathrm{~h}^2-4} \\\\ & \\left(\\mathrm{x}^2+\\mathrm{y}^2-5\\right)^2=4\\left[\\mathrm{x}^2 \\mathrm{y}^2-\\left(\\mathrm{y}^2-1\\right)\\left(\\mathrm{x}^2-4\\right)\\right] \\\\ & \\Rightarrow\\left(\\mathrm{x}^2+\\mathrm{y}^2-5\\right)^2=4\\left[4 \\mathrm{y}^2+\\mathrm{x}^2-4\\right]\\end{aligned}$", "difficulty": "Easy", "source": "Most Important Selected Qs for JEE Advanced", "_book": "68f1ce4cc729e5251bd00430", "_chapterKey": "68f1ce4cc729e5251bd00430__68f8d633530ed81e1968d783__68f8d64a530ed81e1968d79c__68f8d663530ed81e1968d7a6"}]}