{"bookId": "69048808ef55966cf1d71f1d", "moduleId": "6909cd14d60676ac599cb644", "subjectId": "69075cb049e6141a77a59709", "chapterId": "69075cb149e6141a77a59718", "subject": "IOQM", "chapter": "Three Dimensional Geometry", "count": 1, "questions": [{"id": 306489, "subject": "IOQM", "chapter": "Three Dimensional Geometry", "exam": "Engineering", "examName": "Olympiad workbook", "q": "Determine the sum of all possible surface areas of a cube two of whose vertices are $(1,2,0)$ and $(3,3,2)$.", "options": ["A", "B", "C", "D"], "answer": 0, "solution": "$Case-I$:\n<img src=\"https://.app/NEET/Olympiad/rjKoXRRoQ3hJSc1-UBfAF5l0e_XDAIk86yjGNLr517A.original.fullsize.png\"><br>\n\n$\\begin{aligned} \\text { SA } & =6 \\times[\\sqrt{4+1+4}]^2 \\\\ & =54 \\text { sq.unit }{ }^2 \\\\ \\text { Case-II: } & \\end{aligned}$<img src=\"https://.app/NEET/Olympiad/dBSOHpHepqoxSDmyIaS1ap0V92XgdxkoOaZud8bIs8k.original.fullsize.png\"><br>\n\n$2 a^2+9$\n$a=\\frac{3}{\\sqrt{2}} \\quad S A=6\\left(\\frac{9}{2}\\right)=27$ sq unit\n\n$Case-III$:<img src=\"https://.app/NEET/Olympiad/5rMXaUWzbmwZ4MW9wC03sx-b2H42SpVFCZYFaeLjEpU.original.fullsize.png\"><br>\n$\\begin{aligned} & \\sqrt{3} a=3 \\\\ & \\Rightarrow a=\\sqrt{3} \\\\ & S A=6 a^2=6 \\times 3=18 \\text { sq.unit }{ }^2 \\\\ & \\therefore \\text { Possible } S A=18+27+54=99\\end{aligned}$", "difficulty": "Medium", "source": "Olympiad workbook", "_book": "69048808ef55966cf1d71f1d", "_chapterKey": "69048808ef55966cf1d71f1d__6909cd14d60676ac599cb644__69075cb049e6141a77a59709__69075cb149e6141a77a59718"}]}